LICENSE
MANIFEST.in
README.md
certbot_netdot.py
setup.cfg
setup.py
certbot_netdot.egg-info/PKG-INFO
certbot_netdot.egg-info/SOURCES.txt
certbot_netdot.egg-info/dependency_links.txt
certbot_netdot.egg-info/entry_points.txt
certbot_netdot.egg-info/requires.txt
certbot_netdot.egg-info/top_level.txt